pytest_run_parallel/__init__.py
pytest_run_parallel/cpu_detection.py
pytest_run_parallel/plugin.py
pytest_run_parallel/thread_comparator.py
pytest_run_parallel/thread_unsafe_detection.py
pytest_run_parallel/utils.py
pytest_run_parallel-0.7.1.dist-info/licenses/LICENSE
pytest_run_parallel-0.7.1.dist-info/METADATA
pytest_run_parallel-0.7.1.dist-info/WHEEL
pytest_run_parallel-0.7.1.dist-info/entry_points.txt
pytest_run_parallel-0.7.1.dist-info/top_level.txt
pytest_run_parallel-0.7.1.dist-info/RECORD
