Metadata-Version: 2.4
Name: pytest-run-parallel
Version: 0.7.1
Summary: A simple pytest plugin to run tests concurrently
Author: Edgar Margffoy
Maintainer-email: Lysandros Nikolaou <lnikolaou@quansight.com>, Nathan Goldbaum <ngoldbaum@quansight.com>
License: MIT License
Project-URL: Repository, https://github.com/Quansight-Labs/pytest-run-parallel
Classifier: Framework :: Pytest
Classifier: Development Status :: 4 - Beta
Classifier: Intended Audience :: Developers
Classifier: Topic :: Software Development :: Testing
Classifier: Operating System :: OS Independent
Classifier: Programming Language :: Python
Classifier: Programming Language :: Python :: 3.9
Classifier: Programming Language :: Python :: 3.10
Classifier: Programming Language :: Python :: 3.11
Classifier: Programming Language :: Python :: 3.12
Classifier: Programming Language :: Python :: 3.13
Classifier: Programming Language :: Python :: 3.14
Classifier: Programming Language :: Python :: 3 :: Only
Classifier: Programming Language :: Python :: Implementation :: CPython
Classifier: Programming Language :: Python :: Implementation :: PyPy
Classifier: License :: OSI Approved :: MIT License
Requires-Python: >=3.9
License-File: LICENSE
Requires-Dist: pytest>=6.2.0
Provides-Extra: psutil
Requires-Dist: psutil>=6.1.1; extra == "psutil"
Dynamic: license-file
